src/pwm_channel.v
`timescale 1ns/1ps

module pwm_channel #(
  parameter integer PERIOD_CYCLES = 50_000,
  parameter integer LEVELS = 10
) (
  input  wire clk,
  input  wire rst_p,
  input  wire [3:0] level,
  output reg pwm
);

  localparam integer COUNT_WIDTH = (PERIOD_CYCLES < 2) ? 1 : $clog2(PERIOD_CYCLES);
  reg [COUNT_WIDTH-1:0] count;
  integer threshold;

  always @* begin
    if (level >= LEVELS)
      threshold = PERIOD_CYCLES;
    else
      threshold = (PERIOD_CYCLES * level) / LEVELS;
  end

  always @(posedge clk or posedge rst_p) begin
    if (rst_p) begin
      count <= {COUNT_WIDTH{1'b0}};
      pwm   <= 1'b0;
    end else begin
      pwm <= (count < threshold);
      if (count == PERIOD_CYCLES - 1)
        count <= {COUNT_WIDTH{1'b0}};
      else
        count <= count + 1'b1;
    end
  end

endmodule

src/button_onepulse.v
`timescale 1ns/1ps
module button_onepulse #(
  parameter integer STABLE_CYCLES = 1_000_000
) (
  input  wire clk,
  input  wire rst_p,
  input  wire button,
  output reg  pulse
);
  (* ASYNC_REG = "TRUE" *) reg button_meta;
  (* ASYNC_REG = "TRUE" *) reg button_sync;
  localparam integer COUNT_WIDTH = (STABLE_CYCLES < 2) ? 1 : $clog2(STABLE_CYCLES);
  reg [COUNT_WIDTH-1:0] stable_count;
  reg accepted;

  always @(posedge clk or posedge rst_p) begin
    if (rst_p) begin
      button_meta  <= 1'b0;
      button_sync  <= 1'b0;
    end else begin
      button_meta  <= button;
      button_sync  <= button_meta;
    end
  end
  
  always @(posedge clk or posedge rst_p) begin
    if (rst_p) begin
      stable_count <= {COUNT_WIDTH{1'b0}};
      accepted     <= 1'b0;
      pulse        <= 1'b0;
    end else begin
      pulse <= 1'b0;
      if (button_sync == accepted) begin
        stable_count <= {COUNT_WIDTH{1'b0}};
      end else if (stable_count == STABLE_CYCLES - 1) begin
        stable_count <= {COUNT_WIDTH{1'b0}};
        accepted     <= button_sync;
        pulse        <= button_sync;
      end else begin
        stable_count <= stable_count + 1'b1;
      end
    end
  end
endmodule

src/lab3_led_pwm.v
`timescale 1ns/1ps
module lab3_led_pwm #(
  parameter integer CLK_HZ = 50_000_000,
  parameter integer PWM_HZ = 1_000,
  parameter integer LEVELS = 10,
  parameter integer DEBOUNCE_CYCLES = 1_000_000
) (
  input  wire clk_50mhz,
  input  wire rst_p,
  input  wire button,
  output wire [7:0] led
);
  wire press;
  wire pwm;
  reg  [3:0] level;

  button_onepulse #(.STABLE_CYCLES(DEBOUNCE_CYCLES)) u_button (
    .clk(clk_50mhz),
    .rst_p(rst_p),
    .button(button),
    .pulse(press)
  );

  always @(posedge clk_50mhz or posedge rst_p) begin
    if (rst_p)
      level <= 4'd0;
    else if (press)
      level <= (level == LEVELS) ? 4'd0 : level + 1'b1;
  end

  pwm_channel #(.PERIOD_CYCLES(CLK_HZ / PWM_HZ), .LEVELS(LEVELS)) u_pwm (
    .clk(clk_50mhz),
    .rst_p(rst_p),
    .level(level),
    .pwm(pwm)
  );

  assign led = {8{pwm}};
endmodule

sim/tb_led_pwm.sv
`timescale 1ns/1ps

module tb_led_pwm;

  reg clk_50mhz = 0, rst_p = 1, button = 0;
  wire [7:0] led;
  integer checks = 0, high_count, i;

  always #10 clk_50mhz = ~clk_50mhz;

  lab3_led_pwm #(
    .CLK_HZ(1000),
    .PWM_HZ(100),
    .LEVELS(10),
    .DEBOUNCE_CYCLES(2)
  ) dut (
    .clk_50mhz(clk_50mhz),
    .rst_p(rst_p),
    .button(button),
    .led(led)
  );

  task press_button;
  begin
    button = 1;
    repeat(6) @(posedge clk_50mhz);
    button = 0;
    repeat(6) @(posedge clk_50mhz);
  end
  endtask

  task expect_level(input integer expected);
  begin
    wait(dut.u_pwm.count == 0);
    high_count = 0;
    for (i = 0; i < 10; i = i + 1) begin
      @(posedge clk_50mhz);
      #1;
      if (led[0])
        high_count = high_count + 1;
    end
    if (high_count !== expected)
      $fatal(1, "level=%0d high=%0d", expected, high_count);
    checks = checks + 1;
  end
  endtask

  initial begin
    $dumpfile("wave.vcd");
    $dumpvars(0, tb_led_pwm);
    repeat(3) @(posedge clk_50mhz);
    rst_p = 0;
    expect_level(0);
    repeat(3) press_button();
    expect_level(3);
    repeat(7) press_button();
    expect_level(10);
    press_button();
    expect_level(0);
    $display("LAB3_LED_PWM_PASS checks=%0d", checks);
    $finish;
  end

  initial begin
    #20000;
    $fatal(1, "timeout");
  end

endmodule

evidence/03/vscode/wave.vcd
$date
	Tue Sep 22 10:53:22 2026
$end
$version
	Icarus Verilog
$end
$timescale
	1ps
$end
$scope module tb_led_pwm $end
$var wire 8 ! led [7:0] $end
$var reg 1 " button $end
$var reg 1 # clk_50mhz $end
$var reg 1 $ rst_p $end
$var integer 32 % checks [31:0] $end
$var integer 32 & high_count [31:0] $end
$var integer 32 ' i [31:0] $end
$scope module dut $end
$var wire 1 " button $end
$var wire 1 # clk_50mhz $end
$var wire 1 $ rst_p $end
$var wire 1 ( pwm $end
$var wire 1 ) press $end
$var wire 8 * led [7:0] $end
$var parameter 32 + CLK_HZ $end
$var parameter 32 , DEBOUNCE_CYCLES $end
$var parameter 32 - LEVELS $end
$var parameter 32 . PWM_HZ $end
$var reg 4 / level [3:0] $end
$scope module u_button $end
$var wire 1 " button $end
$var wire 1 # clk $end
$var wire 1 $ rst_p $end
$var parameter 32 0 COUNT_WIDTH $end
$var parameter 32 1 STABLE_CYCLES $end
$var reg 1 2 accepted $end
$var reg 1 3 button_meta $end
$var reg 1 4 button_sync $end
$var reg 1 ) pulse $end
$var reg 1 5 stable_count $end
$upscope $end
$scope module u_pwm $end
$var wire 1 # clk $end
$var wire 4 6 level [3:0] $end
$var wire 1 $ rst_p $end
$var parameter 32 7 COUNT_WIDTH $end
$var parameter 32 8 LEVELS $end
$var parameter 32 9 PERIOD_CYCLES $end
$var reg 4 : count [3:0] $end
$var reg 1 ( pwm $end
$var integer 32 ; threshold [31:0] $end
$upscope $end
$upscope $end
$scope task expect_level $end
$var integer 32 < expected [31:0] $end
$upscope $end
$scope task press_button $end
$upscope $end
$upscope $end
$enddefinitions $end
$comment Show the parameter values. $end
$dumpall
b1010 9
b1010 8
b100 7
b10 1
b1 0
b1100100 .
b1010 -
b10 ,
b1111101000 +
$end
#0
$dumpvars
bx <
bx ;
bx :
bx 6
x5
x4
x3
x2
bx /
bx *
x)
x(
bx '
bx &
b0 %
1$
0#
0"
bx !
$end
#10000
b0 ;
04
03
0)
02
05
b0 !
b0 *
0(
b0 :
b0 /
b0 6
1#
#20000
0#
#30000
1#
#40000
0#
#50000
b1 :
b0 '
b0 &
b0 <
0$
1#
#60000
0#
#70000
b10 :
1#
#71000
b1 '
#80000
0#
#90000
b11 :
1#
#91000
b10 '
#100000
0#
#110000
b100 :
1#
#111000
b11 '
#120000
0#
#130000
b101 :
1#
#131000
b100 '
#140000
0#
#150000
b110 :
1#
#151000
b101 '
#160000
0#
#170000
b111 :
1#
#171000
b110 '
#180000
0#
#190000
b1000 :
1#
#191000
b111 '
#200000
0#
#210000
b1001 :
1#
#211000
b1000 '
#220000
0#
#230000
b0 :
1#
#231000
b1001 '
#240000
0#
#250000
b1 :
1#
#251000
1"
b1 %
b1010 '
#260000
0#
#270000
b10 :
13
1#
#280000
0#
#290000
14
b11 :
1#
#300000
0#
#310000
b100 :
15
1#
#320000
0#
#330000
1)
12
05
b101 :
1#
#340000
0#
#350000
b1 ;
b1 /
b1 6
b110 :
0)
1#
#360000
0#
#370000
03
b111 :
0"
1#
#380000
0#
#390000
b1000 :
04
1#
#400000
0#
#410000
15
b1001 :
1#
#420000
0#
#430000
b0 :
02
05
1#
#440000
0#
#450000
b1 :
b11111111 !
b11111111 *
1(
1#
#460000
0#
#470000
b10 :
b0 !
b0 *
0(
1#
#480000
0#
#490000
13
b11 :
1"
1#
#500000
0#
#510000
b100 :
14
1#
#520000
0#
#530000
15
b101 :
1#
#540000
0#
#550000
b110 :
1)
12
05
1#
#560000
0#
#570000
b10 ;
0)
b111 :
b10 /
b10 6
1#
#580000
0#
#590000
b1000 :
1#
#600000
0#
#610000
03
b1001 :
0"
1#
#620000
0#
#630000
b0 :
04
1#
#640000
0#
#650000
15
b1 :
b11111111 !
b11111111 *
1(
1#
#660000
0#
#670000
b10 :
02
05
1#
#680000
0#
#690000
b11 :
b0 !
b0 *
0(
1#
#700000
0#
#710000
b100 :
1#
#720000
0#
#730000
13
b101 :
1"
1#
#740000
0#
#750000
b110 :
14
1#
#760000
0#
#770000
15
b111 :
1#
#780000
0#
#790000
b1000 :
1)
12
05
1#
#800000
0#
#810000
b11 ;
0)
b1001 :
b11 /
b11 6
1#
#820000
0#
#830000
b0 :
1#
#840000
0#
#850000
03
b1 :
b11111111 !
b11111111 *
1(
0"
1#
#860000
0#
#870000
b10 :
04
1#
#880000
0#
#890000
15
b11 :
1#
#900000
0#
#910000
b100 :
b0 !
b0 *
0(
02
05
1#
#920000
0#
#930000
b101 :
1#
#940000
0#
#950000
b110 :
1#
#960000
0#
#970000
b111 :
b11 <
1#
#980000
0#
#990000
b1000 :
1#
#1000000
0#
#1010000
b1001 :
1#
#1020000
0#
#1030000
b0 '
b0 :
1#
#1040000
0#
#1050000
b1 :
b11111111 !
b11111111 *
1(
1#
#1051000
b1 '
b1 &
#1060000
0#
#1070000
b10 :
1#
#1071000
b10 '
b10 &
#1080000
0#
#1090000
b11 :
1#
#1091000
b11 '
b11 &
#1100000
0#
#1110000
b100 :
b0 !
b0 *
0(
1#
#1111000
b100 '
#1120000
0#
#1130000
b101 :
1#
#1131000
b101 '
#1140000
0#
#1150000
b110 :
1#
#1151000
b110 '
#1160000
0#
#1170000
b111 :
1#
#1171000
b111 '
#1180000
0#
#1190000
b1000 :
1#
#1191000
b1000 '
#1200000
0#
#1210000
b1001 :
1#
#1211000
b1001 '
#1220000
0#
#1230000
b0 :
1#
#1231000
1"
b10 %
b1010 '
#1240000
0#
#1250000
13
b1 :
b11111111 !
b11111111 *
1(
1#
#1260000
0#
#1270000
b10 :
14
1#
#1280000
0#
#1290000
15
b11 :
1#
#1300000
0#
#1310000
b100 :
b0 !
b0 *
0(
1)
12
05
1#
#1320000
0#
#1330000
b100 ;
0)
b101 :
b100 /
b100 6
1#
#1340000
0#
#1350000
b110 :
03
0"
1#
#1360000
0#
#1370000
04
b111 :
1#
#1380000
0#
#1390000
b1000 :
15
1#
#1400000
0#
#1410000
02
05
b1001 :
1#
#1420000
0#
#1430000
b0 :
1#
#1440000
0#
#1450000
b1 :
b11111111 !
b11111111 *
1(
1#
#1460000
0#
#1470000
b10 :
13
1"
1#
#1480000
0#
#1490000
14
b11 :
1#
#1500000
0#
#1510000
b100 :
15
1#
#1520000
0#
#1530000
1)
12
05
b101 :
b0 !
b0 *
0(
1#
#1540000
0#
#1550000
b101 ;
b101 /
b101 6
b110 :
0)
1#
#1560000
0#
#1570000
b111 :
1#
#1580000
0#
#1590000
b1000 :
03
0"
1#
#1600000
0#
#1610000
04
b1001 :
1#
#1620000
0#
#1630000
b0 :
15
1#
#1640000
0#
#1650000
02
05
b1 :
b11111111 !
b11111111 *
1(
1#
#1660000
0#
#1670000
b10 :
1#
#1680000
0#
#1690000
b11 :
1#
#1700000
0#
#1710000
b100 :
13
1"
1#
#1720000
0#
#1730000
14
b101 :
1#
#1740000
0#
#1750000
b110 :
b0 !
b0 *
0(
15
1#
#1760000
0#
#1770000
1)
12
05
b111 :
1#
#1780000
0#
#1790000
b110 ;
b110 /
b110 6
b1000 :
0)
1#
#1800000
0#
#1810000
b1001 :
1#
#1820000
0#
#1830000
b0 :
03
0"
1#
#1840000
0#
#1850000
04
b1 :
b11111111 !
b11111111 *
1(
1#
#1860000
0#
#1870000
b10 :
15
1#
#1880000
0#
#1890000
02
05
b11 :
1#
#1900000
0#
#1910000
b100 :
1#
#1920000
0#
#1930000
b101 :
1#
#1940000
0#
#1950000
b110 :
13
1"
1#
#1960000
0#
#1970000
14
b111 :
b0 !
b0 *
0(
1#
#1980000
0#
#1990000
b1000 :
15
1#
#2000000
0#
#2010000
1)
12
05
b1001 :
1#
#2020000
0#
#2030000
b111 ;
b111 /
b111 6
b0 :
0)
1#
#2040000
0#
#2050000
b1 :
b11111111 !
b11111111 *
1(
1#
#2060000
0#
#2070000
b10 :
03
0"
1#
#2080000
0#
#2090000
04
b11 :
1#
#2100000
0#
#2110000
b100 :
15
1#
#2120000
0#
#2130000
02
05
b101 :
1#
#2140000
0#
#2150000
b110 :
1#
#2160000
0#
#2170000
b111 :
1#
#2180000
0#
#2190000
b1000 :
b0 !
b0 *
0(
13
1"
1#
#2200000
0#
#2210000
14
b1001 :
1#
#2220000
0#
#2230000
b0 :
15
1#
#2240000
0#
#2250000
1)
12
05
b1 :
b11111111 !
b11111111 *
1(
1#
#2260000
0#
#2270000
b1000 ;
b1000 /
b1000 6
b10 :
0)
1#
#2280000
0#
#2290000
b11 :
1#
#2300000
0#
#2310000
b100 :
03
0"
1#
#2320000
0#
#2330000
04
b101 :
1#
#2340000
0#
#2350000
b110 :
15
1#
#2360000
0#
#2370000
02
05
b111 :
1#
#2380000
0#
#2390000
b1000 :
1#
#2400000
0#
#2410000
b1001 :
b0 !
b0 *
0(
1#
#2420000
0#
#2430000
b0 :
13
1"
1#
#2440000
0#
#2450000
14
b1 :
b11111111 !
b11111111 *
1(
1#
#2460000
0#
#2470000
b10 :
15
1#
#2480000
0#
#2490000
1)
12
05
b11 :
1#
#2500000
0#
#2510000
b1001 ;
b1001 /
b1001 6
b100 :
0)
1#
#2520000
0#
#2530000
b101 :
1#
#2540000
0#
#2550000
b110 :
03
0"
1#
#2560000
0#
#2570000
04
b111 :
1#
#2580000
0#
#2590000
b1000 :
15
1#
#2600000
0#
#2610000
02
05
b1001 :
1#
#2620000
0#
#2630000
b0 :
b0 !
b0 *
0(
1#
#2640000
0#
#2650000
b1 :
b11111111 !
b11111111 *
1(
1#
#2660000
0#
#2670000
b10 :
13
1"
1#
#2680000
0#
#2690000
14
b11 :
1#
#2700000
0#
#2710000
b100 :
15
1#
#2720000
0#
#2730000
1)
12
05
b101 :
1#
#2740000
0#
#2750000
b1010 ;
b1010 /
b1010 6
b110 :
0)
1#
#2760000
0#
#2770000
b111 :
1#
#2780000
0#
#2790000
b1000 :
03
0"
1#
#2800000
0#
#2810000
04
b1001 :
1#
#2820000
0#
#2830000
b0 :
15
1#
#2840000
0#
#2850000
02
05
b1 :
1#
#2860000
0#
#2870000
b10 :
1#
#2880000
0#
#2890000
b11 :
1#
#2900000
0#
#2910000
b100 :
b1010 <
1#
#2920000
0#
#2930000
b101 :
1#
#2940000
0#
#2950000
b110 :
1#
#2960000
0#
#2970000
b111 :
1#
#2980000
0#
#2990000
b1000 :
1#
#3000000
0#
#3010000
b1001 :
1#
#3020000
0#
#3030000
b0 '
b0 &
b0 :
1#
#3040000
0#
#3050000
b1 :
1#
#3051000
b1 '
b1 &
#3060000
0#
#3070000
b10 :
1#
#3071000
b10 '
b10 &
#3080000
0#
#3090000
b11 :
1#
#3091000
b11 '
b11 &
#3100000
0#
#3110000
b100 :
1#
#3111000
b100 '
b100 &
#3120000
0#
#3130000
b101 :
1#
#3131000
b101 '
b101 &
#3140000
0#
#3150000
b110 :
1#
#3151000
b110 '
b110 &
#3160000
0#
#3170000
b111 :
1#
#3171000
b111 '
b111 &
#3180000
0#
#3190000
b1000 :
1#
#3191000
b1000 '
b1000 &
#3200000
0#
#3210000
b1001 :
1#
#3211000
b1001 '
b1001 &
#3220000
0#
#3230000
b0 :
1#
#3231000
1"
b11 %
b1010 '
b1010 &
#3240000
0#
#3250000
13
b1 :
1#
#3260000
0#
#3270000
b10 :
14
1#
#3280000
0#
#3290000
15
b11 :
1#
#3300000
0#
#3310000
b100 :
1)
12
05
1#
#3320000
0#
#3330000
b0 ;
0)
b101 :
b0 /
b0 6
1#
#3340000
0#
#3350000
b110 :
b0 !
b0 *
0(
03
0"
1#
#3360000
0#
#3370000
04
b111 :
1#
#3380000
0#
#3390000
b1000 :
15
1#
#3400000
0#
#3410000
02
05
b1001 :
1#
#3420000
0#
#3430000
b0 :
1#
#3440000
0#
#3450000
b1 :
1#
#3460000
0#
#3470000
b10 :
b0 <
1#
#3480000
0#
#3490000
b11 :
1#
#3500000
0#
#3510000
b100 :
1#
#3520000
0#
#3530000
b101 :
1#
#3540000
0#
#3550000
b110 :
1#
#3560000
0#
#3570000
b111 :
1#
#3580000
0#
#3590000
b1000 :
1#
#3600000
0#
#3610000
b1001 :
1#
#3620000
0#
#3630000
b0 '
b0 &
b0 :
1#
#3640000
0#
#3650000
b1 :
1#
#3651000
b1 '
#3660000
0#
#3670000
b10 :
1#
#3671000
b10 '
#3680000
0#
#3690000
b11 :
1#
#3691000
b11 '
#3700000
0#
#3710000
b100 :
1#
#3711000
b100 '
#3720000
0#
#3730000
b101 :
1#
#3731000
b101 '
#3740000
0#
#3750000
b110 :
1#
#3751000
b110 '
#3760000
0#
#3770000
b111 :
1#
#3771000
b111 '
#3780000
0#
#3790000
b1000 :
1#
#3791000
b1000 '
#3800000
0#
#3810000
b1001 :
1#
#3811000
b1001 '
#3820000
0#
#3830000
b0 :
1#
#3831000
b100 %
b1010 '
